xapo_sdk/__init__.py
xapo_sdk/xapo_api.py
xapo_sdk/xapo_tools.py
xapo_sdk/xapo_utils.py
xapo_sdk-0.2.2.dist-info/DESCRIPTION.rst
xapo_sdk-0.2.2.dist-info/METADATA
xapo_sdk-0.2.2.dist-info/metadata.json
xapo_sdk-0.2.2.dist-info/RECORD
xapo_sdk-0.2.2.dist-info/top_level.txt
xapo_sdk-0.2.2.dist-info/WHEEL
