Metadata-Version: 2.0
Name: xapo-sdk
Version: 0.2.2
Summary: Xapo bitcoin sdk & tools
Home-page: https://github.com/xapo/python-sdk
Author: Federico Repond
Author-email: federico.repond@leapsight.com
License: BSD
Keywords: xapo_sdk
Platform: UNKNOWN
Classifier: Development Status :: 4 - Beta
Classifier: Intended Audience :: Developers
Classifier: License :: OSI Approved :: BSD License
Classifier: Natural Language :: English
Classifier: Programming Language :: Python :: 2
Classifier: Programming Language :: Python :: 2.6
Classifier: Programming Language :: Python :: 2.7
Classifier: Programming Language :: Python :: 3
Classifier: Programming Language :: Python :: 3.3
Classifier: Programming Language :: Python :: 3.4
